easydb/__init__.py
easydb/domain.py
easydb/http.py
easydb_http_client-0.0.3.dist-info/LICENSE
easydb_http_client-0.0.3.dist-info/METADATA
easydb_http_client-0.0.3.dist-info/WHEEL
easydb_http_client-0.0.3.dist-info/top_level.txt
easydb_http_client-0.0.3.dist-info/RECORD
